{
	"PurchaseOrder": [{
		"PONumber": "PO1",
		"PurchaseOrderNo": "1001",
		"POInitiator": "Mehul",
		"Plant" : "Plant 1",
		"Vendor": "Vendor 1",
		"PODate": "12/06/2020",
		"POStatus": "In Approval",
		"src": "sap-icon://pdf-attachment",
		"Amount": "1000",
		"CurrencyCode": "INR",
		"Status": "Approved",
		"icon": "Purchase Order No",
		"DocumentType": "Document Type 1",
		"PODescription": "XYZ...."

	}, {
		"PONumber": "PO2",
		"PurchaseOrderNo": "1002",
		"POInitiator": "Krishna",
			"Plant" : "Plant 2",
		"Vendor": "Vendor 2",
		"PODate": "15/06/2020",
		"POStatus": "In Approval",
		"PossiblePOStatus": "INAP",
		"src": "sap-icon://pdf-attachment",
		"Amount": "2000",
		"CurrencyCode": "INR",
		"Status": "Reject",
		"icon": "Purchase Order No",
		"DocumentType": "Document Type 2",
		"PODescription": "XYZ...."
	}, {
		"PONumber": "PO3",
		"PurchaseOrderNo": "1003",
		"POInitiator": "Surya",
			"Plant" : "Plant 3",
		"Vendor": "Vendor 3",
		"PODate": "18/06/2020",
		"POStatus": "In Rejection",
		"PossiblePOStatus": "APPR",
		"src": "sap-icon://pdf-attachment",
		"Amount": "3000",
		"CurrencyCode": "INR",
		"Status": "INAP",
		"icon": "Purchase Order No",
		"DocumentType": "Document Type 3",
		"PODescription": "XYZ...."
	}, {
		"PONumber": "PO4",
		"PurchaseOrderNo": "1004",
		"POInitiator": "Rajni",
			"Plant" : "Plant 4",
		"Vendor": "Vendor 4",
		"PODate": "20/06/2020",
		"POStatus": "In Approval",
		"PossiblePOStatus": "INQR",
		"src": "sap-icon://pdf-attachment",
		"Amount": "4000",
		"CurrencyCode": "INR",
		"Status": "INQR",
		"icon": "Purchase Order No",
		"DocumentType": "Document Type 4",
			"PODescription" : "XYZ...." 
	}, {
		"PONumber": "PO5",
		"PurchaseOrderNo": "1005",
		"POInitiator": "Vijay",
			"Plant" : "Plant 5",
		"Vendor": "Vendor 5",
		"PODate": "22/06/2020",
		"POStatus": "In Approval",
		"PossiblePOStatus": "INAP",
		"src": "sap-icon://pdf-attachment",
		"Amount": "5000",
		"CurrencyCode": "INR",
		"Status": "Approved",
		"icon": "Purchase Order No",
		"DocumentType": "Document Type 5",
			"PODescription" : "XYZ...." 
	}]

}